{
  "status": "Succeeded",
  "succeeded": true,
  "failed": false,
  "finished": true,
  "recognitionResult": {
    "lines": [
      {
        "boundingBox": [
          16,
          5,
          193,
          6,
          192,
          18,
          15,
          17
        ],
        "text": "Number of days' treatment",
        "words": [
          {
            "boundingBox": [
              15,
              7,
              69,
              7,
              70,
              19,
              15,
              18
            ],
            "text": "Number"
          },
          {
            "boundingBox": [
              73,
              7,
              87,
              7,
              88,
              19,
              73,
              19
            ],
            "text": "of"
          },
          {
            "boundingBox": [
              90,
              7,
              124,
              7,
              124,
              19,
              90,
              19
            ],
            "text": "days'"
          },
          {
            "boundingBox": [
              126,
              7,
              193,
              8,
              193,
              18,
              126,
              19
            ],
            "text": "treatment"
          }
        ]
      },
      {
        "boundingBox": [
          16,
          18,
          185,
          19,
          184,
          32,
          15,
          31
        ],
        "text": "N.B. Ensure dose is stated",
        "words": [
          {
            "boundingBox": [
              15,
              19,
              45,
              20,
              45,
              31,
              16,
              30
            ],
            "text": "N.B."
          },
          {
            "boundingBox": [
              46,
              20,
              89,
              20,
              89,
              32,
              46,
              31
            ],
            "text": "Ensure"
          },
          {
            "boundingBox": [
              94,
              20,
              123,
              21,
              123,
              32,
              94,
              32
            ],
            "text": "dose"
          },
          {
            "boundingBox": [
              127,
              21,
              138,
              21,
              138,
              32,
              126,
              32
            ],
            "text": "is"
          },
          {
            "boundingBox": [
              140,
              21,
              180,
              21,
              179,
              32,
              140,
              32
            ],
            "text": "stated"
          }
        ]
      },
      {
        "boundingBox": [
          318,
          6,
          412,
          7,
          411,
          19,
          317,
          18
        ],
        "text": "NHS Number:",
        "words": [
          {
            "boundingBox": [
              317,
              8,
              346,
              8,
              346,
              19,
              317,
              19
            ],
            "text": "NHS"
          },
          {
            "boundingBox": [
              350,
              8,
              412,
              8,
              411,
              20,
              350,
              19
            ],
            "text": "Number:"
          }
        ]
      },
      {
        "boundingBox": [
          15,
          35,
          121,
          36,
          120,
          49,
          14,
          48
        ],
        "text": "Endorsements",
        "words": [
          {
            "boundingBox": [
              15,
              36,
              115,
              38,
              115,
              49,
              16,
              49
            ],
            "text": "Endorsements"
          }
        ]
      },
      {
        "boundingBox": [
          138,
          33,
          431,
          35,
          430,
          50,
          137,
          49
        ],
        "text": "Fultium-D3 800unit capsules (Internis",
        "words": [
          {
            "boundingBox": [
              141,
              36,
              227,
              36,
              227,
              50,
              141,
              49
            ],
            "text": "Fultium-D3"
          },
          {
            "boundingBox": [
              232,
              36,
              290,
              36,
              290,
              50,
              232,
              50
            ],
            "text": "800unit"
          },
          {
            "boundingBox": [
              293,
              36,
              362,
              36,
              361,
              51,
              293,
              50
            ],
            "text": "capsules"
          },
          {
            "boundingBox": [
              365,
              36,
              429,
              36,
              429,
              51,
              365,
              51
            ],
            "text": "(Internis"
          }
        ]
      },
      {
        "boundingBox": [
          140,
          49,
          309,
          50,
          309,
          70,
          139,
          68
        ],
        "text": "Pharmaceuticals Ltd)",
        "words": [
          {
            "boundingBox": [
              140,
              51,
              272,
              51,
              272,
              70,
              142,
              69
            ],
            "text": "Pharmaceuticals"
          },
          {
            "boundingBox": [
              273,
              51,
              309,
              51,
              308,
              70,
              273,
              70
            ],
            "text": "Ltd)"
          }
        ]
      },
      {
        "boundingBox": [
          141,
          68,
          251,
          69,
          250,
          84,
          140,
          83
        ],
        "text": "take one daily",
        "words": [
          {
            "boundingBox": [
              140,
              70,
              174,
              70,
              174,
              84,
              140,
              83
            ],
            "text": "take"
          },
          {
            "boundingBox": [
              181,
              70,
              207,
              70,
              207,
              84,
              181,
              84
            ],
            "text": "one"
          },
          {
            "boundingBox": [
              214,
              70,
              249,
              70,
              249,
              85,
              214,
              84
            ],
            "text": "daily"
          }
        ]
      },
      {
        "boundingBox": [
          141,
          86,
          229,
          87,
          228,
          101,
          140,
          99
        ],
        "text": "28 capsule",
        "words": [
          {
            "boundingBox": [
              142,
              87,
              160,
              87,
              160,
              100,
              142,
              100
            ],
            "text": "28"
          },
          {
            "boundingBox": [
              167,
              87,
              226,
              88,
              225,
              101,
              167,
              101
            ],
            "text": "capsule"
          }
        ]
      },
      {
        "boundingBox": [
          143,
          100,
          346,
          101,
          345,
          121,
          142,
          120
        ],
        "text": "seven day blister supplies",
        "words": [
          {
            "boundingBox": [
              141,
              103,
              187,
              102,
              188,
              121,
              141,
              120
            ],
            "text": "seven"
          },
          {
            "boundingBox": [
              192,
              102,
              222,
              102,
              222,
              122,
              192,
              121
            ],
            "text": "day"
          },
          {
            "boundingBox": [
              224,
              102,
              275,
              102,
              275,
              122,
              225,
              122
            ],
            "text": "blister"
          },
          {
            "boundingBox": [
              276,
              102,
              341,
              102,
              342,
              121,
              277,
              122
            ],
            "text": "supplies"
          }
        ]
      },
      {
        "boundingBox": [
          142,
          135,
          340,
          136,
          339,
          152,
          141,
          151
        ],
        "text": "Furosemide 40mg tablets",
        "words": [
          {
            "boundingBox": [
              143,
              139,
              233,
              137,
              233,
              152,
              143,
              151
            ],
            "text": "Furosemide"
          },
          {
            "boundingBox": [
              240,
              137,
              281,
              137,
              281,
              153,
              240,
              152
            ],
            "text": "40mg"
          },
          {
            "boundingBox": [
              286,
              137,
              338,
              138,
              338,
              152,
              286,
              153
            ],
            "text": "tablets"
          }
        ]
      },
      {
        "boundingBox": [
          141,
          154,
          174,
          155,
          173,
          166,
          142,
          167
        ],
        "text": "2bd",
        "words": [
          {
            "boundingBox": [
              144,
              154,
              171,
              155,
              170,
              167,
              144,
              166
            ],
            "text": "2bd"
          }
        ]
      },
      {
        "boundingBox": [
          142,
          169,
          222,
          170,
          221,
          184,
          141,
          183
        ],
        "text": "112 tablet",
        "words": [
          {
            "boundingBox": [
              143,
              170,
              170,
              171,
              170,
              185,
              144,
              184
            ],
            "text": "112"
          },
          {
            "boundingBox": [
              174,
              171,
              221,
              171,
              221,
              185,
              175,
              185
            ],
            "text": "tablet"
          }
        ]
      },
      {
        "boundingBox": [
          139,
          185,
          343,
          186,
          342,
          205,
          138,
          204
        ],
        "text": "seven day blister supplies",
        "words": [
          {
            "boundingBox": [
              141,
              187,
              188,
              187,
              189,
              205,
              142,
              205
            ],
            "text": "seven"
          },
          {
            "boundingBox": [
              192,
              187,
              222,
              187,
              223,
              206,
              193,
              206
            ],
            "text": "day"
          },
          {
            "boundingBox": [
              225,
              187,
              276,
              187,
              276,
              206,
              225,
              206
            ],
            "text": "blister"
          },
          {
            "boundingBox": [
              276,
              187,
              342,
              187,
              342,
              206,
              276,
              206
            ],
            "text": "supplies"
          }
        ]
      },
      {
        "boundingBox": [
          140,
          218,
          423,
          219,
          423,
          239,
          139,
          238
        ],
        "text": "Isosorbide mononitrate 20mg tablets",
        "words": [
          {
            "boundingBox": [
              140,
              220,
              224,
              219,
              223,
              239,
              140,
              239
            ],
            "text": "Isosorbide"
          },
          {
            "boundingBox": [
              226,
              219,
              320,
              219,
              319,
              239,
              226,
              239
            ],
            "text": "mononitrate"
          },
          {
            "boundingBox": [
              324,
              219,
              368,
              219,
              368,
              240,
              323,
              239
            ],
            "text": "20mg"
          },
          {
            "boundingBox": [
              370,
              219,
              426,
              219,
              425,
              240,
              369,
              240
            ],
            "text": "tablets"
          }
        ]
      },
      {
        "boundingBox": [
          142,
          237,
          296,
          238,
          295,
          253,
          141,
          252
        ],
        "text": "take one twice daily",
        "words": [
          {
            "boundingBox": [
              141,
              239,
              175,
              239,
              175,
              253,
              141,
              253
            ],
            "text": "take"
          },
          {
            "boundingBox": [
              181,
              239,
              209,
              239,
              209,
              254,
              181,
              253
            ],
            "text": "one"
          },
          {
            "boundingBox": [
              213,
              239,
              253,
              239,
              253,
              254,
              213,
              254
            ],
            "text": "twice"
          },
          {
            "boundingBox": [
              259,
              239,
              294,
              239,
              293,
              254,
              259,
              254
            ],
            "text": "daily"
          }
        ]
      },
      {
        "boundingBox": [
          143,
          254,
          220,
          255,
          219,
          269,
          142,
          268
        ],
        "text": "56 tablet",
        "words": [
          {
            "boundingBox": [
              143,
              255,
              161,
              255,
              161,
              269,
              143,
              269
            ],
            "text": "56"
          },
          {
            "boundingBox": [
              166,
              255,
              212,
              256,
              211,
              270,
              166,
              269
            ],
            "text": "tablet"
          }
        ]
      },
      {
        "boundingBox": [
          142,
          271,
          340,
          272,
          339,
          287,
          141,
          286
        ],
        "text": "four week blister supplies",
        "words": [
          {
            "boundingBox": [
              142,
              273,
              174,
              273,
              174,
              287,
              142,
              286
            ],
            "text": "four"
          },
          {
            "boundingBox": [
              178,
              273,
              217,
              273,
              217,
              287,
              178,
              287
            ],
            "text": "week"
          },
          {
            "boundingBox": [
              223,
              273,
              270,
              273,
              271,
              288,
              223,
              287
            ],
            "text": "blister"
          },
          {
            "boundingBox": [
              274,
              273,
              337,
              273,
              338,
              288,
              275,
              288
            ],
            "text": "supplies"
          }
        ]
      },
      {
        "boundingBox": [
          142,
          305,
          339,
          306,
          338,
          321,
          141,
          320
        ],
        "text": "Mirtazapine 15mg tablets",
        "words": [
          {
            "boundingBox": [
              142,
              307,
              232,
              307,
              232,
              322,
              142,
              320
            ],
            "text": "Mirtazapine"
          },
          {
            "boundingBox": [
              239,
              307,
              280,
              307,
              280,
              322,
              239,
              322
            ],
            "text": "15mg"
          },
          {
            "boundingBox": [
              284,
              307,
              337,
              308,
              337,
              321,
              284,
              322
            ],
            "text": "tablets"
          }
        ]
      },
      {
        "boundingBox": [
          140,
          320,
          277,
          322,
          276,
          340,
          139,
          339
        ],
        "text": "take one at night",
        "words": [
          {
            "boundingBox": [
              140,
              322,
              176,
              322,
              177,
              340,
              141,
              340
            ],
            "text": "take"
          },
          {
            "boundingBox": [
              181,
              322,
              210,
              322,
              211,
              341,
              182,
              341
            ],
            "text": "one"
          },
          {
            "boundingBox": [
              214,
              322,
              234,
              322,
              234,
              341,
              215,
              341
            ],
            "text": "at"
          },
          {
            "boundingBox": [
              233,
              322,
              276,
              322,
              276,
              341,
              233,
              341
            ],
            "text": "night"
          }
        ]
      },
      {
        "boundingBox": [
          142,
          339,
          218,
          339,
          217,
          354,
          141,
          353
        ],
        "text": "28 tablet",
        "words": [
          {
            "boundingBox": [
              144,
              339,
              163,
              340,
              163,
              354,
              144,
              354
            ],
            "text": "28"
          },
          {
            "boundingBox": [
              166,
              340,
              213,
              341,
              213,
              355,
              166,
              354
            ],
            "text": "tablet"
          }
        ]
      },
      {
        "boundingBox": [
          144,
          353,
          346,
          354,
          345,
          374,
          143,
          373
        ],
        "text": "seven day blister supplies",
        "words": [
          {
            "boundingBox": [
              143,
              356,
              189,
              355,
              190,
              374,
              143,
              373
            ],
            "text": "seven"
          },
          {
            "boundingBox": [
              194,
              355,
              224,
              355,
              224,
              375,
              194,
              374
            ],
            "text": "day"
          },
          {
            "boundingBox": [
              226,
              355,
              277,
              355,
              277,
              375,
              227,
              375
            ],
            "text": "blister"
          },
          {
            "boundingBox": [
              278,
              355,
              343,
              355,
              344,
              374,
              279,
              375
            ],
            "text": "supplies"
          }
        ]
      },
      {
        "boundingBox": [
          140,
          388,
          355,
          387,
          356,
          408,
          141,
          409
        ],
        "text": "4 items on this prescription",
        "words": [
          {
            "boundingBox": [
              143,
              389,
              156,
              389,
              156,
              409,
              143,
              408
            ],
            "text": "4"
          },
          {
            "boundingBox": [
              154,
              389,
              203,
              390,
              203,
              409,
              155,
              409
            ],
            "text": "items"
          },
          {
            "boundingBox": [
              204,
              390,
              225,
              390,
              226,
              409,
              204,
              409
            ],
            "text": "on"
          },
          {
            "boundingBox": [
              227,
              390,
              259,
              390,
              259,
              409,
              227,
              409
            ],
            "text": "this"
          },
          {
            "boundingBox": [
              260,
              390,
              350,
              388,
              351,
              408,
              261,
              409
            ],
            "text": "prescription"
          }
        ]
      }
    ]
  }
}